pyzgoubi-0.7.1.data/data/share/pyzgoubi/examples/emma-find-closed-orbit.py
pyzgoubi-0.7.1.data/data/share/pyzgoubi/examples/emma-find-magnetaperture.py
pyzgoubi-0.7.1.data/data/share/pyzgoubi/examples/emma-track.py
pyzgoubi-0.7.1.data/data/share/pyzgoubi/examples/emma-tune-diagram.py
pyzgoubi-0.7.1.data/data/share/pyzgoubi/examples/emma-twiss-profile.py
pyzgoubi-0.7.1.data/data/share/pyzgoubi/examples/emma.py
pyzgoubi-0.7.1.data/data/share/pyzgoubi/examples/kek-ffag.py
pyzgoubi-0.7.1.data/data/share/pyzgoubi/examples/quickstart.py
pyzgoubi-0.7.1.data/data/share/pyzgoubi/examples/quickstart2.py
pyzgoubi-0.7.1.data/data/share/pyzgoubi/test/00-bunch_read_write.py
pyzgoubi-0.7.1.data/data/share/pyzgoubi/test/00-lattice.py
pyzgoubi-0.7.1.data/data/share/pyzgoubi/test/00-param-get-set.py
pyzgoubi-0.7.1.data/data/share/pyzgoubi/test/10-basic_pyzgoubi_test.py
pyzgoubi-0.7.1.data/data/share/pyzgoubi/test/10-dvalue.py
pyzgoubi-0.7.1.data/data/share/pyzgoubi/test/10-values_in_res.py
pyzgoubi-0.7.1.data/data/share/pyzgoubi/test/20-drift_tof_ascii_fai.py
pyzgoubi-0.7.1.data/data/share/pyzgoubi/test/20-drift_tof_bin_fai.py
pyzgoubi-0.7.1.data/data/share/pyzgoubi/test/20-inout_YTZP_ascii_fai.py
pyzgoubi-0.7.1.data/data/share/pyzgoubi/test/20-inout_YTZP_ascii_plt.py
pyzgoubi-0.7.1.data/data/share/pyzgoubi/test/25-inout_YTZP_ascii_fai_bunch.py
pyzgoubi-0.7.1.data/data/share/pyzgoubi/test/25-inout_YTZP_bin_fai_bunch.py
pyzgoubi-0.7.1.data/data/share/pyzgoubi/test/30-JAERI.py
pyzgoubi-0.7.1.data/data/share/pyzgoubi/test/30-emma-find-closed-orbit.py
pyzgoubi-0.7.1.data/data/share/pyzgoubi/test/30-kek-ffag.py
pyzgoubi-0.7.1.data/data/share/pyzgoubi/test/40-bunch_loss.py
pyzgoubi-0.7.1.data/data/share/pyzgoubi/test/40-inout_track_bunch.py
pyzgoubi-0.7.1.data/data/share/pyzgoubi/test/41-labplot.py
pyzgoubi-0.7.1.data/data/share/pyzgoubi/test/45-bunch_loss_mt.py
pyzgoubi-0.7.1.data/data/share/pyzgoubi/test/45-inout_track_bunch_mt.py
pyzgoubi-0.7.1.dist-info/AUTHORS
pyzgoubi-0.7.1.dist-info/COPYING
pyzgoubi-0.7.1.dist-info/METADATA
pyzgoubi-0.7.1.dist-info/WHEEL
pyzgoubi-0.7.1.dist-info/top_level.txt
pyzgoubi-0.7.1.dist-info/RECORD
