Metadata-Version: 2.1
Name: pyzgoubi
Version: 0.7.1
Summary: PyZgoubi is an interface to the Zgoubi particle tracker written in python.
Home-page: http://sourceforge.net/projects/pyzgoubi/
Author: Sam Tygier
Author-email: sam.tygier@manchester.ac.uk
License: GNU GENERAL PUBLIC LICENSE
Platform: UNKNOWN
Classifier: Development Status :: 5 - Production/Stable
Classifier: Intended Audience :: Science/Research
Classifier: Topic :: Scientific/Engineering :: Physics
Classifier: License :: OSI Approved :: GNU General Public License (GPL)
Classifier: Programming Language :: Python :: 2.7
